dtuimldmtools/__init__.py
dtuimldmtools/clustering/__init__.py
dtuimldmtools/clustering/utils.py
dtuimldmtools/crossvalidation/__init__.py
dtuimldmtools/crossvalidation/implementations.py
dtuimldmtools/data/__init__.py
dtuimldmtools/data/body.mat
dtuimldmtools/data/courses.txt
dtuimldmtools/data/digits.mat
dtuimldmtools/data/faithful.mat
dtuimldmtools/data/faithful.txt
dtuimldmtools/data/female.txt
dtuimldmtools/data/iris.csv
dtuimldmtools/data/iris.mat
dtuimldmtools/data/iris.xls
dtuimldmtools/data/male.txt
dtuimldmtools/data/nanonose.xls
dtuimldmtools/data/readme_male_female_data.txt
dtuimldmtools/data/stopWords.txt
dtuimldmtools/data/synth1.mat
dtuimldmtools/data/synth2.mat
dtuimldmtools/data/synth3.mat
dtuimldmtools/data/synth4.mat
dtuimldmtools/data/synth5.mat
dtuimldmtools/data/synth6.mat
dtuimldmtools/data/synth7.mat
dtuimldmtools/data/textDocs.txt
dtuimldmtools/data/wildfaces.mat
dtuimldmtools/data/wildfaces_grayscale.mat
dtuimldmtools/data/wine.mat
dtuimldmtools/data/wine2.mat
dtuimldmtools/data/xor.mat
dtuimldmtools/data/zipdata.mat
dtuimldmtools/data/messy_data/README.txt
dtuimldmtools/data/messy_data/messy_data.data
dtuimldmtools/data_utils/__init__.py
dtuimldmtools/data_utils/bootstrap.py
dtuimldmtools/data_utils/categoric2numeric.py
dtuimldmtools/data_utils/ranges.py
dtuimldmtools/data_utils/remove_zeros.py
dtuimldmtools/models/__init__.py
dtuimldmtools/models/bin_classifier_ensemble.py
dtuimldmtools/models/nn_trainer.py
dtuimldmtools/plots/__init__.py
dtuimldmtools/plots/plots.py
dtuimldmtools/plots/visualize_db.py
dtuimldmtools/plots/visualize_nn.py
dtuimldmtools/statistics/__init__.py
dtuimldmtools/statistics/similarity_measure.py
dtuimldmtools/statistics/statistics.py
dtuimldmtools-0.1.6.dist-info/LICENSE
dtuimldmtools-0.1.6.dist-info/METADATA
dtuimldmtools-0.1.6.dist-info/WHEEL
dtuimldmtools-0.1.6.dist-info/top_level.txt
dtuimldmtools-0.1.6.dist-info/RECORD
