Metadata-Version: 2.2
Name: dtuimldmtools
Version: 0.1.6
Summary: "DTU 02450 Tools"
Author: DTU Compute, Section for Cognitive Systems
Author-email: 02450@compute.dtu.dk
Platform: any
Classifier: Development Status :: 4 - Beta
Classifier: Intended Audience :: Education
Classifier: Operating System :: OS Independent
Classifier: Programming Language :: Python :: 3 :: Only
Classifier: Programming Language :: Python :: 3.8
Classifier: Programming Language :: Python :: 3.9
Classifier: Programming Language :: Python :: 3.10
Classifier: Programming Language :: Python :: 3.11
Classifier: Topic :: Education
Classifier: Topic :: Scientific/Engineering :: Mathematics
Requires-Python: >=3.8
License-File: LICENSE
Requires-Dist: matplotlib
Requires-Dist: scikit-learn
Requires-Dist: numpy
Requires-Dist: torch
Requires-Dist: nltk
Requires-Dist: xlrd
Requires-Dist: scipy
Requires-Dist: apyori
Requires-Dist: importlib_resources
Requires-Dist: pandas
Provides-Extra: dev
Requires-Dist: matplotlib; extra == "dev"
Requires-Dist: scikit-learn; extra == "dev"
Requires-Dist: numpy; extra == "dev"
Requires-Dist: torch; extra == "dev"
Requires-Dist: nltk; extra == "dev"
Requires-Dist: xlrd; extra == "dev"
Requires-Dist: scipy; extra == "dev"
Requires-Dist: importlib_resources; extra == "dev"
Requires-Dist: apyori; extra == "dev"
Requires-Dist: pandas; extra == "dev"
Requires-Dist: black; extra == "dev"
Requires-Dist: pytest; extra == "dev"
Requires-Dist: flake8; extra == "dev"
Requires-Dist: twine; extra == "dev"
Requires-Dist: build; extra == "dev"
Dynamic: provides-extra
Dynamic: requires-dist
Dynamic: requires-python
